.editorconfig
.gitattributes
.gitignore
LICENSE.md
MANIFEST.in
README.md
setup.cfg
setup.py
scripts/LONG_DESCRIPTION.txt
scripts/__init__.py
scripts/git.py
scripts/setup.py
scripts/utils.py
scripts/version.py.in
scripts/versioning.py
src/zvit/__init__.py
src/zvit/__main__.py
src/zvit/tfevents.py
src/zvit/version.py
src/zvit/writer.py
src/zvit.egg-info/PKG-INFO
src/zvit.egg-info/SOURCES.txt
src/zvit.egg-info/dependency_links.txt
src/zvit.egg-info/entry_points.txt
src/zvit.egg-info/not-zip-safe
src/zvit.egg-info/requires.txt
src/zvit.egg-info/top_level.txt
src/zvit.egg-info/version.txt
src/zvit/bin/__init__.py
src/zvit/bin/demo.py
src/zvit/pb/__init__.py
src/zvit/pb/crc.py
src/zvit/pb/crc_native.c
src/zvit/pb/pebble.py